<annotation>
	<folder>深度学习采集螺丝</folder>
	<filename>Camera MV-GE502C#A9FE9BF0-Snapshot-20230216-140709-910-193662986126.BMP</filename>
	<path>F:\项目资料\23年项目资料\车顶无人化项目\深度学习采集螺丝\Camera MV-GE502C#A9FE9BF0-Snapshot-20230216-140709-910-193662986126.BMP</path>
	<source>
		<database>Unknown</database>
	</source>
	<size>
		<width>2592</width>
		<height>1944</height>
		<depth>3</depth>
	</size>
	<segmented>0</segmented>
	<object>
		<name>luosi</name>
		<pose>Unspecified</pose>
		<truncated>0</truncated>
		<difficult>0</difficult>
		<bndbox>
			<xmin>1119</xmin>
			<ymin>1102</ymin>
			<xmax>1315</xmax>
			<ymax>1331</ymax>
		</bndbox>
	</object>
</annotation>
